libhamming/__init__.py
libhamming/hamming.cp36-win32.pyd
libhamming-0.3.dist-info/LICENSE
libhamming-0.3.dist-info/METADATA
libhamming-0.3.dist-info/WHEEL
libhamming-0.3.dist-info/top_level.txt
libhamming-0.3.dist-info/RECORD
