Metadata-Version: 2.1
Name: libhamming
Version: 0.3
Summary: Library for hamming code
Home-page: https://github.com/hex-in/libhammingcode.git
Author: Heyn
Author-email: heyunhuan@gmail.com
License: GPLv3
Keywords: hamming,hamming code
Platform: any
Classifier: Development Status :: 3 - Alpha
Classifier: Intended Audience :: Developers
Classifier: Topic :: Software Development :: Build Tools
Classifier: License :: OSI Approved :: MIT License
Classifier: Programming Language :: Python :: 3
Classifier: Programming Language :: Python :: 3.6
Classifier: Programming Language :: Python :: Implementation :: CPython
Classifier: Programming Language :: Python :: Implementation :: PyPy
